aliyunsdkdyplsapi/__init__.py
aliyunsdkdyplsapi/endpoint.py
aliyunsdkdyplsapi/request/__init__.py
aliyunsdkdyplsapi/request/v20170525/AddAxnTrackNoRequest.py
aliyunsdkdyplsapi/request/v20170525/AddSecretBlacklistRequest.py
aliyunsdkdyplsapi/request/v20170525/BindAxbRequest.py
aliyunsdkdyplsapi/request/v20170525/BindAxgRequest.py
aliyunsdkdyplsapi/request/v20170525/BindAxnExtensionRequest.py
aliyunsdkdyplsapi/request/v20170525/BindAxnRequest.py
aliyunsdkdyplsapi/request/v20170525/BindBatchAxgRequest.py
aliyunsdkdyplsapi/request/v20170525/BuySecretNoRequest.py
aliyunsdkdyplsapi/request/v20170525/CancelPickUpWaybillRequest.py
aliyunsdkdyplsapi/request/v20170525/CreateAxgGroupRequest.py
aliyunsdkdyplsapi/request/v20170525/CreatePickUpWaybillPreQueryRequest.py
aliyunsdkdyplsapi/request/v20170525/CreatePickUpWaybillRequest.py
aliyunsdkdyplsapi/request/v20170525/DeleteAxgGroupRequest.py
aliyunsdkdyplsapi/request/v20170525/DeleteSecretBlacklistRequest.py
aliyunsdkdyplsapi/request/v20170525/GetSecretAsrDetailRequest.py
aliyunsdkdyplsapi/request/v20170525/GetTotalPublicUrlRequest.py
aliyunsdkdyplsapi/request/v20170525/LockSecretNoRequest.py
aliyunsdkdyplsapi/request/v20170525/OperateAxgGroupRequest.py
aliyunsdkdyplsapi/request/v20170525/OperateBlackNoRequest.py
aliyunsdkdyplsapi/request/v20170525/QueryPhoneNoAByTrackNoRequest.py
aliyunsdkdyplsapi/request/v20170525/QueryRecordFileDownloadUrlRequest.py
aliyunsdkdyplsapi/request/v20170525/QuerySecretNoDetailRequest.py
aliyunsdkdyplsapi/request/v20170525/QuerySecretNoRemainRequest.py
aliyunsdkdyplsapi/request/v20170525/QuerySubsIdRequest.py
aliyunsdkdyplsapi/request/v20170525/QuerySubscriptionDetailRequest.py
aliyunsdkdyplsapi/request/v20170525/ReleaseSecretNoRequest.py
aliyunsdkdyplsapi/request/v20170525/UnbindSubscriptionRequest.py
aliyunsdkdyplsapi/request/v20170525/UnlockSecretNoRequest.py
aliyunsdkdyplsapi/request/v20170525/UpdateSubscriptionRequest.py
aliyunsdkdyplsapi/request/v20170525/__init__.py
aliyun_python_sdk_dyplsapi-1.3.5.dist-info/LICENSE
aliyun_python_sdk_dyplsapi-1.3.5.dist-info/METADATA
aliyun_python_sdk_dyplsapi-1.3.5.dist-info/WHEEL
aliyun_python_sdk_dyplsapi-1.3.5.dist-info/top_level.txt
aliyun_python_sdk_dyplsapi-1.3.5.dist-info/RECORD
